src/cli.py
src/main.py
src/configs/config.py
src/configs/replacements.py
src/configs/rules.py
src/configs/gen/def_conf.py
src/metadata/info.py
src/mutils/build_tex.py
src/mutils/check_if_eq.py
src/mutils/check_if_table.py
src/mutils/finalize.py
src/mutils/find_files.py
src/mutils/fix_file_path.py
src/mutils/fix_missing_conf.py
src/mutils/fix_title.py
src/mutils/format_body.py
src/mutils/merge_conf.py
src/mutils/prompts.py
src/mutils/update_conf.py
src/utils/config_fetch.py
src/utils/convert.py
src/utils/convert_file.py
src/utils/logger.py
src/utils/tex/environments/figure.py
src/utils/tex/environments/listings.py
src/utils/tex/environments/mathsec.py
src/utils/tex/environments/quotes.py
src/utils/tex/environments/table.py
src/utils/tex/environments/tex_enumerate.py
src/utils/tex/parser/body.py
src/utils/tex/parser/headings.py
src/utils/tex/parser/table_parse.py
src/utils/tex/text/format.py
src/utils/tex/text/replace_util.py
simtex-0.4.2b1.dist-info/LICENSE
simtex-0.4.2b1.dist-info/METADATA
simtex-0.4.2b1.dist-info/WHEEL
simtex-0.4.2b1.dist-info/entry_points.txt
simtex-0.4.2b1.dist-info/top_level.txt
simtex-0.4.2b1.dist-info/RECORD
