Metadata-Version: 2.1
Name: simtex
Version: 0.4.2b1
Summary: Convert your markdown or text files into LaTeX/pdf with one command!
Home-page: https://github.com/iaacornus/simtex
Author: James Aaron Erang (iaacornus)
Author-email: iaacornus.devel@gmail.com
Maintainer: James Aaron Erang (iaacornus)
Maintainer-email: iaacornus.devel@gmail.com
License: GPL v3
Classifier: Development Status :: 4 - Beta
Classifier: Programming Language :: Python :: 3.10
Classifier: License :: OSI Approved :: GNU General Public License v3 (GPLv3)
Classifier: Natural Language :: English
Classifier: Operating System :: OS Independent
Requires-Python: >=3.10
License-File: LICENSE
Requires-Dist: rich (==12.4.4)
Requires-Dist: requests (==2.28.1)
